MANIFEST.in
README.md
scratch_dir.py
setup.py
scratch_dir.egg-info/PKG-INFO
scratch_dir.egg-info/SOURCES.txt
scratch_dir.egg-info/dependency_links.txt
scratch_dir.egg-info/top_level.txt