Metadata-Version: 1.1
Name: scratch-dir
Version: 1.0.0
Summary: Unit test mixin which creates a scratch directory
Home-page: https://github.com/bodylabs/scratch-dir
Author: Body Labs
Author-email: paul.melnikow@bodylabs.com, alex@bodylabs.com, david.smith@bodylabs.com
License: MIT
Platform: UNKNOWN
Classifier: Development Status :: 3 - Alpha
Classifier: Intended Audience :: Developers
Classifier: License :: OSI Approved :: BSD License
Classifier: Operating System :: OS Independent
Classifier: Programming Language :: Python
